frogml_storage/__init__.py
frogml_storage/_artifactory_api.py
frogml_storage/_environment.py
frogml_storage/_log_config.py
frogml_storage/_storage_utils.py
frogml_storage/_utils.py
frogml_storage/authentication/_authentication_utils.py
frogml_storage/authentication/models/_auth_config.py
frogml_storage/cli/_frogml_cli.py
frogml_storage/cli/_login_cli.py
frogml_storage/cli/commands/_login_command.py
frogml_storage/cli/models/_cli_login_arguments.py
frogml_storage/cli/utils/_cli_utils.py
frogml_storage/cli/utils/_login_checks_utility.py
frogml_storage/constants.py
frogml_storage/dataset_manifest.py
frogml_storage/entity_manifest.py
frogml_storage/exceptions/checksum_verification_error.py
frogml_storage/exceptions/validation_error.py
frogml_storage/frog_ml.py
frogml_storage/frogml_entity_type_info.py
frogml_storage/http/__init__.py
frogml_storage/http/http_client.py
frogml_storage/model_manifest.py
frogml_storage/models/_download_context.py
frogml_storage/models/frogml_dataset_version.py
frogml_storage/models/frogml_entity_version.py
frogml_storage/models/frogml_model_version.py
frogml_storage/serialization_metadata.py
frogml_storage/storage.py
frogml_storage/utils/_input_checks_utility.py
frogml_storage-0.11.2.dist-info/LICENSE
frogml_storage-0.11.2.dist-info/METADATA
frogml_storage-0.11.2.dist-info/WHEEL
frogml_storage-0.11.2.dist-info/entry_points.txt
frogml_storage-0.11.2.dist-info/RECORD
