Metadata-Version: 2.3
Name: frogml-storage
Version: 0.11.2
Summary: JFrog ML Storage package
Author: JFrog
Requires-Python: >=3.9,<3.13
Classifier: Operating System :: OS Independent
Classifier: Programming Language :: Python :: 3
Classifier: Programming Language :: Python :: 3.9
Classifier: Programming Language :: Python :: 3.10
Classifier: Programming Language :: Python :: 3.11
Classifier: Programming Language :: Python :: 3.12
Classifier: Programming Language :: Python :: Implementation :: CPython
Requires-Dist: pydantic
Requires-Dist: requests
Requires-Dist: tqdm
Requires-Dist: typer
Project-URL: Homepage, https://github.com/jfrog/frogml
